ciftostr/__init__.py
ciftostr/__main__.py
ciftostr/ciftostr.py
ciftostr/cli.py
ciftostr-0.2.0.dist-info/AUTHORS.rst
ciftostr-0.2.0.dist-info/LICENSE
ciftostr-0.2.0.dist-info/METADATA
ciftostr-0.2.0.dist-info/WHEEL
ciftostr-0.2.0.dist-info/entry_points.txt
ciftostr-0.2.0.dist-info/top_level.txt
ciftostr-0.2.0.dist-info/RECORD
