Metadata-Version: 2.1
Name: ciftostr
Version: 0.2.0
Summary: A small utility to convert crystal structures in CIF format into TOPAS STR format.
Home-page: https://github.com/rowlesmr/ciftostr
Author: Matthew Rowles
Author-email: rowlesmr@gmail.com
License: Apache-2.0
Project-URL: Documentation, https://ciftostr.readthedocs.io/
Project-URL: Changelog, https://ciftostr.readthedocs.io/en/latest/changelog.html
Project-URL: Issue Tracker, https://github.com/rowlesmr/ciftostr/issues
Keywords: diffraction,X-ray,neutron,synchrotron,powder diffraction,CIF,crystallography,Rietveld,TOPAS
Platform: UNKNOWN
Classifier: Development Status :: 4 - Beta
Classifier: Intended Audience :: End Users/Desktop
Classifier: Intended Audience :: Science/Research
Classifier: License :: OSI Approved :: Apache Software License
Classifier: Operating System :: Unix
Classifier: Operating System :: POSIX
Classifier: Operating System :: Microsoft :: Windows
Classifier: Programming Language :: Python
Classifier: Programming Language :: Python :: 3
Classifier: Programming Language :: Python :: 3 :: Only
Classifier: Programming Language :: Python :: 3.6
Classifier: Programming Language :: Python :: 3.7
Classifier: Programming Language :: Python :: 3.8
Classifier: Programming Language :: Python :: 3.9
Classifier: Programming Language :: Python :: Implementation :: CPython
Classifier: Programming Language :: Python :: Implementation :: PyPy
Classifier: Topic :: Utilities
Classifier: Topic :: Scientific/Engineering
Requires-Python: >=3.6
Requires-Dist: PyCifRW (>=4.4.3)
Requires-Dist: PySimpleGUI (>=4.39.1)
